ss7/__init__.py
ss7/core.py
ss7-1.0.1.dist-info/LICENSE
ss7-1.0.1.dist-info/METADATA
ss7-1.0.1.dist-info/WHEEL
ss7-1.0.1.dist-info/top_level.txt
ss7-1.0.1.dist-info/RECORD
